kditransform/__init__.py
kditransform/kdi_discretizer.py
kditransform/kdi_transformer.py
kditransform/ksum.py
kditransform-1.2.0.dist-info/licenses/LICENSE
kditransform-1.2.0.dist-info/METADATA
kditransform-1.2.0.dist-info/WHEEL
kditransform-1.2.0.dist-info/top_level.txt
kditransform-1.2.0.dist-info/zip-safe
kditransform-1.2.0.dist-info/RECORD
