Metadata-Version: 2.4
Name: kditransform
Version: 1.2.0
Summary: Kernel density integral transformation
Home-page: http://github.com/calvinmccarter/kditransform
Author: Calvin McCarter
Author-email: Calvin McCarter <mccarter.calvin@gmail.com>
Maintainer: Calvin McCarter
Maintainer-email: Calvin McCarter <mccarter.calvin@gmail.com>
Project-URL: Homepage, http://github.com/calvinmccarter/kditransform
Keywords: preprocessing,integral transformation,kernel smoothing
Classifier: Development Status :: 3 - Alpha
Classifier: Intended Audience :: Developers
Classifier: Intended Audience :: Science/Research
Classifier: License :: OSI Approved
Classifier: Operating System :: MacOS
Classifier: Operating System :: Microsoft :: Windows
Classifier: Operating System :: POSIX
Classifier: Operating System :: Unix
Classifier: Programming Language :: Python
Classifier: Programming Language :: Python :: 3.6
Classifier: Programming Language :: Python :: 3.7
Classifier: Programming Language :: Python :: 3.8
Classifier: Programming Language :: Python :: 3.9
Classifier: Topic :: Scientific/Engineering
Classifier: Topic :: Software Development
License-File: LICENSE
Requires-Dist: numba>=0.48
Requires-Dist: numpy
Requires-Dist: scikit-learn>=1.6.0
Requires-Dist: scipy>=1.0
Dynamic: author
Dynamic: home-page
Dynamic: license-file
Dynamic: maintainer
